{
    "Employees": [
        {
            "Employee_Name": "Carlos",
            "Employee_SecondName": "Pérez",
            "Role_ID": 1,
            "Shop_ID": 1,
            "Employee_EMail": "carlosperez@empresa.com",
            "Employee_Phone": "600123451",
            "Employee_Password": "Contra1"
        },
        {
            "Employee_Name": "Lucía",
            "Employee_SecondName": "Martínez", 
            "Role_ID": 1,
            "Shop_ID": 1,
            "Employee_EMail": "luciamartinez@empresa.com",
            "Employee_Phone": "600123452",
            "Employee_Password": "Contra2"
        },
        {
            "Employee_Name": "Alberto",
            "Employee_SecondName": "Olleta",
            "Role_ID": 1,
            "Shop_ID": 1,
            "Employee_EMail": "albertoolleta@empresa.com",
            "Employee_Phone": "600123453",
            "Employee_Password": "XUTpCIl4FQ"
        }
    ]
}